{
    "data": [
        {
            "title": "Enduro",
            "category": "Atari",
            "price": "99.99",
            "description": "Um jogo sem Fim",
            "producers": [
                "Atari"
            ],
            "cover": "enduro.jpg"
        },
        {
            "title": "Turbo Game",
            "category": "Console",
            "price": "99.99",
            "description": "Nitendo do Paraguai",
            "producers": [
                "Sem Marca"
            ],
            "cover": "turbo-game.jpg"
        },
        {
            "title": "River Raiv",
            "category": "Atari",
            "price": "99.99",
            "description": "Tiro para todo lado na navinha",
            "producers": [
                "Atari"
            ],
            "cover": "river-raid.jpg"
        }
    ]
}